data/__init__.py
data/openbuildings/__init__.py
data/openbuildings/openbuildingsdownload.py
data/openbuildings/s2countries.py
data/osm/__init__.py
data/osm/geofabrik_sources.py
data/osm/osm2geojson.py
data/osm/osmdownload.py
data/osm/osminfo.py
data/osm/osmpub.py
data/osm/osmreplication.py
vdownload/__init__.py
vdownload/openbuildings/__init__.py
vdownload/openbuildings/openbuildings.py
vdownload/openbuildings/s2countries.py
vdownload/osm/__init__.py
vdownload/osm/geofabrik_sources.py
vdownload/osm/osm2geojson.py
vdownload/osm/osmdownload.py
vdownload/osm/osminfo.py
vdownload/osm/osmpub.py
vdownload/osm/osmreplication.py
vdownload-1.0.0.dist-info/LICENSE
vdownload-1.0.0.dist-info/METADATA
vdownload-1.0.0.dist-info/WHEEL
vdownload-1.0.0.dist-info/entry_points.txt
vdownload-1.0.0.dist-info/top_level.txt
vdownload-1.0.0.dist-info/RECORD
