Metadata-Version: 2.1
Name: vdownload
Version: 1.0.0
Summary: A Powerful Geospatial Data Downloader
Home-page: https://github.com/thangqd/vdownload
Author: Thang Quach
Author-email: quachdongthang@gmail.com
Classifier: Programming Language :: Python :: 3
Classifier: Environment :: Console
Classifier: Topic :: Scientific/Engineering :: GIS
Classifier: License :: OSI Approved :: MIT License
Classifier: Operating System :: OS Independent
License-File: LICENSE
Requires-Dist: tqdm ~=4.66.2
Requires-Dist: requests ~=2.31.0
Requires-Dist: shapely ~=2.0.1
Requires-Dist: osmium ~=3.7.0
